[{"_path":"/resources/courses","_dir":"resources","_draft":false,"_partial":false,"_locale":"","title":"Courses","description":"","meta":[{"name":"description","content":"Vue.js courses"},{"name":"og:title","content":"Courses"},{"name":"og:type","content":"website"},{"name":"og:url","content":"https://awesome-vue.js.org/resources/courses.html"},{"name":"og:image","content":"https://awesome-vue.js.org/hero.png"},{"name":"og:description","content":"Vue.js courses"},{"name":"twitter:card","content":"summary"},{"name":"twitter:title","content":"Courses"},{"name":"twitter:description","content":"Vue.js courses"},{"name":"twitter:image:src","content":"https://awesome-vue.js.org/hero.png"}],"_type":"markdown","_id":"content:resources:courses.md","_source":"content","_file":"resources/courses.md","_stem":"resources/courses","_extension":"md"},{"_path":"/resources/examples","_dir":"resources","_draft":false,"_partial":false,"_locale":"","title":"Examples","description":"","meta":[{"name":"description","content":"Showcase of Vue.js web application examples"},{"name":"og:title","content":"Examples"},{"name":"og:type","content":"website"},{"name":"og:url","content":"https://awesome-vue.js.org/resources/examples.html"},{"name":"og:image","content":"https://awesome-vue.js.org/hero.png"},{"name":"og:description","content":"Showcase of Vue.js web application examples"},{"name":"twitter:card","content":"summary"},{"name":"twitter:title","content":"Examples"},{"name":"twitter:description","content":"Showcase of Vue.js web application examples"},{"name":"twitter:image:src","content":"https://awesome-vue.js.org/hero.png"}],"_type":"markdown","_id":"content:resources:examples.md","_source":"content","_file":"resources/examples.md","_stem":"resources/examples","_extension":"md"}]